<Properties StartupConfiguration="{1E6D0602-4FAF-4DAF-AF13-6F4EC4D15496}|Default">
  <MonoDevelop.Ide.Workspace ActiveConfiguration="Debug" />
  <MonoDevelop.Ide.ItemProperties.sprint0 PreferredExecutionTarget="MonoDevelop.Default" />
  <MonoDevelop.Ide.DebuggingService.Breakpoints>
    <BreakpointStore />
  </MonoDevelop.Ide.DebuggingService.Breakpoints>
  <MonoDevelop.Ide.DebuggingService.PinnedWatches />
  <MonoDevelop.Ide.Workbench ActiveDocument="sprint0/SpriteRectangle.cs">
    <Files>
      <File FileName="sprint0/Sprite.cs" Line="101" Column="1" />
      <File FileName="sprint0/Player.cs" Line="30" Column="10" />
      <File FileName="sprint0/Game1.cs" Line="117" Column="1" />
      <File FileName="sprint0/PlayerFactory.cs" Line="32" Column="1" />
      <File FileName="sprint0/EnemyFactory.cs" Line="33" Column="10" />
      <File FileName="sprint0/ResetCommand.cs" Line="36" Column="37" />
      <File FileName="sprint0/Enemy.cs" Line="15" Column="1" />
      <File FileName="sprint0/Program.cs" Line="4" Column="1" />
      <File FileName="sprint0/ISprite.cs" Line="17" Column="6" />
      <File FileName="sprint0/ShootProjectileCommand.cs" Line="70" Column="14" />
      <File FileName="sprint0/KeyboardController.cs" Line="48" Column="1" />
      <File FileName="sprint0/Attacking.cs" Line="40" Column="14" />
      <File FileName="sprint0/ICommand.cs" Line="11" Column="29" />
      <File FileName="sprint0/Damaged.cs" Line="41" Column="14" />
      <File FileName="sprint0/Content/Content.mgcb" Line="59" Column="1" />
      <File FileName="../.nuget/packages/monogame.content.builder.task/3.8.1.303/build/MonoGame.Content.Builder.Task.targets" Line="142" Column="5" />
      <File FileName="sprint0/SpriteFactory.cs" Line="25" Column="1" />
      <File FileName="sprint0/Link.cs" Line="52" Column="10" />
      <File FileName="sprint0/ItemFactory.cs" Line="42" Column="13" />
      <File FileName="sprint0/BlockFactory.cs" Line="28" Column="10" />
      <File FileName="sprint0/SpriteRectangle.cs" Line="65" Column="10" />
    </Files>
    <Pads>
      <Pad Id="ProjectPad">
        <State name="__root__">
          <Node name="sprint0" expanded="True">
            <Node name="sprint0" expanded="True">
              <Node name="Content" expanded="True" />
            </Node>
          </Node>
        </State>
      </Pad>
      <Pad Id="MonoDevelop.Debugger.WatchPad">
        <State />
      </Pad>
    </Pads>
  </MonoDevelop.Ide.Workbench>
  <MultiItemStartupConfigurations />
</Properties>