<?xml version="1.0" encoding="UTF-8" ?>
<XnaContent>
    <Pointers>
        <WestRoom>Room8</WestRoom>
        <EastRoom>Room12</EastRoom>
        <SouthRoom>Room7</SouthRoom>
    </Pointers>
    <Meta>
        <Name>Room11</Name>
    </Meta>
    <Asset>
		<Item>
			<ObjectType>Sprite</ObjectType>
			<ObjectName>Dungeon</ObjectName>
			<Location>150 120</Location>
		</Item>
        <Item>
            <ObjectType>Sprite</ObjectType>
            <ObjectName>DungeonDoorEast</ObjectName>
            <Location>598 264</Location>
        </Item>
        <Item>
            <ObjectType>Sprite</ObjectType>
            <ObjectName>DungeonDoorWest</ObjectName>
            <Location>174 264</Location>
        </Item>
        <Item>
            <ObjectType>Sprite</ObjectType>
            <ObjectName>DungeonBadDoorSouth</ObjectName>
            <Location>374 408</Location>
        </Item>
		<Item>
			<ObjectType>Block</ObjectType>
			<ObjectName>DungeonBlock</ObjectName>
			<Location>275 250</Location>
		</Item>
		<Item>
			<ObjectType>Block</ObjectType>
			<ObjectName>DungeonBlock</ObjectName>
			<Location>500 250</Location>
		</Item>
		<Item>
			<ObjectType>Block</ObjectType>
			<ObjectName>DungeonBlock</ObjectName>
			<Location>275 315</Location>
		</Item>
		<Item>
			<ObjectType>Block</ObjectType>
			<ObjectName>DungeonBlock</ObjectName>
			<Location>500 315</Location>
		</Item>
        <Item>
            <ObjectType>Enemy</ObjectType>
            <ObjectName>Goriya</ObjectName>
            <Location>352 256</Location>
        </Item>
        <Item>
            <ObjectType>Enemy</ObjectType>
            <ObjectName>Goriya</ObjectName>
            <Location>352 352</Location>
        </Item>
        <Item>
            <ObjectType>Enemy</ObjectType>
            <ObjectName>Goriya</ObjectName>
            <Location>480 304</Location>
        </Item>
        <Item>
            <ObjectType>Player</ObjectType>
            <ObjectName>Link</ObjectName>
            <Location>366 352</Location>
        </Item>
    </Asset>
</XnaContent>

