<?xml version="1.0" encoding="UTF-8" ?>
<XnaContent>
    <Pointers>
        <EastRoom>Room1</EastRoom>
    </Pointers>
    <Meta>
        <Name>Room2</Name>
    </Meta>
    <Asset>
        <Item>
            <ObjectType>Sprite</ObjectType>
            <ObjectName>Dungeon</ObjectName>
            <Location>272 224</Location>
        </Item>
        <Item>
            <ObjectType>Block</ObjectType>
            <ObjectName>DungeonNorthWall</ObjectName>
            <Location>272 224</Location>
        </Item>
        <Item>
            <ObjectType>Block</ObjectType>
            <ObjectName>DungeonSouthWall</ObjectName>
            <Location>272 368</Location>
        </Item>
        <Item>
            <ObjectType>Block</ObjectType>
            <ObjectName>DungeonEastWall</ObjectName>
            <Location>496 224</Location>
        </Item>
        <Item>
            <ObjectType>Block</ObjectType>
            <ObjectName>DungeonWestWall</ObjectName>
            <Location>272 224</Location>
        </Item>
        <Item>
            <ObjectType>Door</ObjectType>
            <ObjectName>DungeonDoorEast</ObjectName>
            <Location>496 296</Location>
        </Item>
        <Item>
            <ObjectType>Enemy</ObjectType>
            <ObjectName>Keese</ObjectName>
            <Location>320 272</Location>
        </Item>
        <Item>
            <ObjectType>Enemy</ObjectType>
            <ObjectName>Keese</ObjectName>
            <Location>304 304</Location>
        </Item>
        <Item>
            <ObjectType>Enemy</ObjectType>
            <ObjectName>Keese</ObjectName>
            <Location>320 336</Location>
        </Item>
    </Asset>
</XnaContent>

